odoo/addons/website_sale_invoice_address/README.rst
odoo/addons/website_sale_invoice_address/__init__.py
odoo/addons/website_sale_invoice_address/__manifest__.py
odoo/addons/website_sale_invoice_address/i18n/ca.po
odoo/addons/website_sale_invoice_address/i18n/es.po
odoo/addons/website_sale_invoice_address/i18n/website_sale_invoice_address.pot
odoo/addons/website_sale_invoice_address/models/__init__.py
odoo/addons/website_sale_invoice_address/models/sale_order.py
odoo/addons/website_sale_invoice_address/models/website.py
odoo/addons/website_sale_invoice_address/readme/CONTRIBUTORS.rst
odoo/addons/website_sale_invoice_address/readme/DESCRIPTION.rst
odoo/addons/website_sale_invoice_address/readme/USAGE.rst
odoo/addons/website_sale_invoice_address/static/description/icon.png
odoo/addons/website_sale_invoice_address/static/description/index.html
odoo/addons/website_sale_invoice_address/static/src/js/website_sale_invoice_address_tour.js
odoo/addons/website_sale_invoice_address/tests/__init__.py
odoo/addons/website_sale_invoice_address/tests/test_website_sale_invoice_address.py
odoo/addons/website_sale_invoice_address/views/assets.xml
odoo12_addon_website_sale_invoice_address-12.0.1.0.0.99.dev8.dist-info/METADATA
odoo12_addon_website_sale_invoice_address-12.0.1.0.0.99.dev8.dist-info/WHEEL
odoo12_addon_website_sale_invoice_address-12.0.1.0.0.99.dev8.dist-info/top_level.txt
odoo12_addon_website_sale_invoice_address-12.0.1.0.0.99.dev8.dist-info/RECORD
